<annotation>
  <folder>Aqua-resize</folder>
  <filename>IMG20210518190836</filename>
  <path>C:\Users\USER\Documents\Dzakwan\bangkit\grab&amp;go\Dataset\Aqua-resize\IMG20210518190836.jpg</path>
  <source>
    <database>Unknown</database>
  </source>
  <size>
    <width>512</width>
    <height>512</height>
    <depth>3</depth>
  </size>
  <segmented>0</segmented>
  <object>
    <name>aqua</name>
    <pose>Unspecified</pose>
    <truncated>0</truncated>
    <difficult>0</difficult>
    <bndbox>
      <xmin>235</xmin>
      <ymin>133</ymin>
      <xmax>364</xmax>
      <ymax>375</ymax>
    </bndbox>
  </object>
</annotation>
